{"activities":[{"id":0,"workout_key":"","name":"Morning Run","description":"","rpe":0,"type":"","weight":86,"ftp":0,"zones":null,"start_point":{"Lat":0,"Lng":0},"end_point":{"Lat":0,"Lng":0},"location_city":"","location_state":"","location_country":"","map":{"id":"","polyline":"","summary_polyline":""},"timestamp":1512732364,"start_time":1512732364,"moving_time":30,"elapsed_time":94,"time_zone":"","lap_timestamp_list":null,"distance":31,"total_elevation_gain":1.8898926,"total_elevation_loss":-1.9498901,"max_elevation":835.92,"min_elevation":835.11,"average_speed":1.2796224,"max_speed":2.375,"average_cadence":88,"max_cadence":104,"min_cadence":76,"average_stride_length":0,"max_stride_length":0,"min_stride_length":0,"average_ground_time":144.41667,"max_ground_time":230,"min_ground_time":35,"average_oscillation":7.421705,"max_oscillation":14.035787,"min_oscillation":0.1598702,"average_power":37.604168,"max_power":261,"average_heart_rate":0,"max_heart_rate":0,"average_leg_spring":34.044273,"calories":0,"stress":0,"max_vertical_stiffness":0.4717564444199768,"seconds_in_zones":null,"power_durations":[261,247.41667,215.15,163.575,113.333336,60.166668,0,0,0,0,0,0,0,0,0,0,0,0,0,0,0,0,0,0,0,0,0,0,0,0,0,0,0],"manufacturer":0,"serial_number":0,"product":0,"battery_voltage":0,"software_version":0,"public":false,"deleted":false,"workout_id":"","user_key":null,"timestamp_key":null,"total_power_key":null,"horizontal_power_key":null,"vertical_power_key":null,"form_power_key":null,"elevation_power_key":null,"heart_rate_key":null,"impact_key":null,"cadence_key":null,"ground_time_key":null,"oscillation_key":null,"leg_spring_key":null,"stress_key":null,"distance_key":null,"device_distance_key":null,"speed_key":null,"device_speed_key":null,"elevation_key":null,"device_elevation_key":null,"location_key":null,"file_path":"","updated_time":"2017-12-09T11:49:02.146879Z"},{"id":0,"workout_key":"","name":"Morning Run","description":"","rpe":0,"type":"","weight":86,"ftp":0,"zones":null,"start_point":{"Lat":0,"Lng":0},"end_point":{"Lat":0,"Lng":0},"location_city":"","location_state":"","location_country":"","map":{"id":"","polyline":"","summary_polyline":""},"timestamp":1512811202,"start_time":1512811202,"moving_time":2350,"elapsed_time":2684,"time_zone":"","lap_timestamp_list":null,"distance":6232,"total_elevation_gain":79.28027,"total_elevation_loss":-73.3103,"max_elevation":839.98,"min_elevation":806.84,"average_speed":2.6528714,"max_speed":3.5390625,"average_cadence":81,"max_cadence":86,"min_cadence":42,"average_stride_length":0,"max_stride_length":0,"min_stride_length":0,"average_ground_time":296.0282,"max_ground_time":1392,"min_ground_time":244,"average_oscillation":7.0941725,"max_oscillation":12.714737,"min_oscillation":1.5678736,"average_power":207.62175,"max_power":305,"average_heart_rate":0,"max_heart_rate":0,"average_leg_spring":12.046863,"calories":0,"stress":0,"max_vertical_stiffness":0.3490105653379697,"seconds_in_zones":null,"power_durations":[305,303.58334,301.85,301,298.71667,296.45834,283.18332,270.31946,263.51666,262.12167,259.50555,257.02142,255.02708,252.83333,252.61917,247.21611,241.34708,239.17027,232.18333,0,0,0,0,0,0,0,0,0,0,0,0,0,0],"manufacturer":0,"serial_number":0,"product":0,"battery_voltage":0,"software_version":0,"public":false,"deleted":false,"workout_id":"","user_key":null,"timestamp_key":null,"total_power_key":null,"horizontal_power_key":null,"vertical_power_key":null,"form_power_key":null,"elevation_power_key":null,"heart_rate_key":null,"impact_key":null,"cadence_key":null,"ground_time_key":null,"oscillation_key":null,"leg_spring_key":null,"stress_key":null,"distance_key":null,"device_distance_key":null,"speed_key":null,"device_speed_key":null,"elevation_key":null,"device_elevation_key":null,"location_key":null,"file_path":"","updated_time":"2017-12-09T11:49:04.617179Z"},{"id":0,"workout_key":"","name":"Noon Run","description":"","rpe":0,"type":"","weight":86,"ftp":0,"zones":null,"start_point":{"Lat":0,"Lng":0},"end_point":{"Lat":0,"Lng":0},"location_city":"","location_state":"","location_country":"","map":{"id":"","polyline":"","summary_polyline":""},"timestamp":1514118696,"start_time":1514118696,"moving_time":5916,"elapsed_time":6404,"time_zone":"","lap_timestamp_list":null,"distance":12245,"total_elevation_gain":146.4602,"total_elevation_loss":-121.40021,"max_elevation":796.91,"min_elevation":755.93,"average_speed":2.0727189,"max_speed":3.2929688,"average_cadence":71,"max_cadence":85,"min_cadence":43,"average_stride_length":0,"max_stride_length":0,"min_stride_length":0,"average_ground_time":543.2643,"max_ground_time":1350,"min_ground_time":68,"average_oscillation":7.515228,"max_oscillation":19.135471,"min_oscillation":3.108173,"average_power":167.31815,"max_power":293,"average_heart_rate":0,"max_heart_rate":0,"average_leg_spring":12.536492,"calories":0,"stress":0,"max_vertical_stiffness":0.3720103872629746,"seconds_in_zones":null,"power_durations":[293,287.91666,281.9,273.425,271.26666,264.69168,242.27083,240.28612,237.5625,235.89833,234.33472,233.48334,231.85938,231.18333,230.20416,228.37389,224.81416,221.08028,222.36354,195.533,181.63847,181.28857,180.77074,179.34953,174.00583,0,0,0,0,0,0,0,0],"manufacturer":0,"serial_number":0,"product":0,"battery_voltage":0,"software_version":0,"public":false,"deleted":false,"workout_id":"","user_key":null,"timestamp_key":null,"total_power_key":null,"horizontal_power_key":null,"vertical_power_key":null,"form_power_key":null,"elevation_power_key":null,"heart_rate_key":null,"impact_key":null,"cadence_key":null,"ground_time_key":null,"oscillation_key":null,"leg_spring_key":null,"stress_key":null,"distance_key":null,"device_distance_key":null,"speed_key":null,"device_speed_key":null,"elevation_key":null,"device_elevation_key":null,"location_key":null,"file_path":"","updated_time":"2017-12-24T14:42:04.976046Z"},{"id":0,"workout_key":"","name":"Morning Run","description":"","rpe":0,"type":"","weight":86,"ftp":0,"zones":null,"start_point":{"Lat":0,"Lng":0},"end_point":{"Lat":0,"Lng":0},"location_city":"","location_state":"","location_country":"","map":{"id":"","polyline":"","summary_polyline":""},"timestamp":1515319538,"start_time":1515319538,"moving_time":4160,"elapsed_time":4406,"time_zone":"","lap_timestamp_list":null,"distance":10416,"total_elevation_gain":110.33966,"total_elevation_loss":-96.60968,"max_elevation":784.02,"min_elevation":748.82,"average_speed":2.4931588,"max_speed":3.0625,"average_cadence":80,"max_cadence":270,"min_cadence":43,"average_stride_length":0,"max_stride_length":0,"min_stride_length":0,"average_ground_time":301.5356,"max_ground_time":1364,"min_ground_time":244,"average_oscillation":7.369617,"max_oscillation":8.153544,"min_oscillation":1.5108626,"average_power":214.76453,"max_power":278,"average_heart_rate":0,"max_heart_rate":0,"average_leg_spring":12.901079,"calories":0,"stress":0,"max_vertical_stiffness":0.33884735859383186,"seconds_in_zones":null,"power_durations":[278,274.16666,271.5,265.25,262.76666,260.25833,255.29584,252.56667,251.25417,249.73334,248.40555,246.52975,245.71042,246.32408,245.86917,243.85722,240.9275,237.71472,235.17667,232.2915,229.88431,225.39691,0,0,0,0,0,0,0,0,0,0,0],"manufacturer":0,"serial_number":0,"product":0,"battery_voltage":0,"software_version":0,"public":false,"deleted":false,"workout_id":"","user_key":null,"timestamp_key":null,"total_power_key":null,"horizontal_power_key":null,"vertical_power_key":null,"form_power_key":null,"elevation_power_key":null,"heart_rate_key":null,"impact_key":null,"cadence_key":null,"ground_time_key":null,"oscillation_key":null,"leg_spring_key":null,"stress_key":null,"distance_key":null,"device_distance_key":null,"speed_key":null,"device_speed_key":null,"elevation_key":null,"device_elevation_key":null,"location_key":null,"file_path":"","updated_time":"2018-01-08T08:27:22.915427Z"},{"id":0,"workout_key":"","name":"Morning Run","description":"","rpe":0,"type":"","weight":86,"ftp":0,"zones":null,"start_point":{"Lat":0,"Lng":0},"end_point":{"Lat":0,"Lng":0},"location_city":"","location_state":"","location_country":"","map":{"id":"","polyline":"","summary_polyline":""},"timestamp":1515486964,"start_time":1515486964,"moving_time":4222,"elapsed_time":4640,"time_zone":"","lap_timestamp_list":null,"distance":10274,"total_elevation_gain":114.940186,"total_elevation_loss":-119.89014,"max_elevation":750.13,"min_elevation":717.62,"average_speed":2.4252703,"max_speed":3.734375,"average_cadence":79,"max_cadence":191,"min_cadence":43,"average_stride_length":0,"max_stride_length":0,"min_stride_length":0,"average_ground_time":336.5961,"max_ground_time":1361,"min_ground_time":116,"average_oscillation":7.241147,"max_oscillation":19.259277,"min_oscillation":3.0033622,"average_power":198.59198,"max_power":321,"average_heart_rate":0,"max_heart_rate":0,"average_leg_spring":12.807581,"calories":0,"stress":0,"max_vertical_stiffness":0.3779026334581066,"seconds_in_zones":null,"power_durations":[321,314.5,305.05,293,286.05,279.11667,269.2125,261.6861,258.09167,257.53333,253.55,249.13095,250.17397,248.17314,247.485,246.11833,240.535,228.18333,221.60458,224.6935,222.29973,215.09631,0,0,0,0,0,0,0,0,0,0,0],"manufacturer":0,"serial_number":0,"product":0,"battery_voltage":0,"software_version":0,"public":false,"deleted":false,"workout_id":"","user_key":null,"timestamp_key":null,"total_power_key":null,"horizontal_power_key":null,"vertical_power_key":null,"form_power_key":null,"elevation_power_key":null,"heart_rate_key":null,"impact_key":null,"cadence_key":null,"ground_time_key":null,"oscillation_key":null,"leg_spring_key":null,"stress_key":null,"distance_key":null,"device_distance_key":null,"speed_key":null,"device_speed_key":null,"elevation_key":null,"device_elevation_key":null,"location_key":null,"file_path":"","updated_time":"2018-01-09T10:51:09.379073Z"},{"id":0,"workout_key":"","name":"Morning Run","description":"","rpe":0,"type":"","weight":86,"ftp":0,"zones":null,"start_point":{"Lat":0,"Lng":0},"end_point":{"Lat":0,"Lng":0},"location_city":"","location_state":"","location_country":"","map":{"id":"","polyline":"","summary_polyline":""},"timestamp":1515490548,"start_time":1515490548,"moving_time":726,"elapsed_time":1056,"time_zone":"","lap_timestamp_list":null,"distance":8851,"total_elevation_gain":47.409973,"total_elevation_loss":-44.99994,"max_elevation":750.13,"min_elevation":717.63,"average_speed":1.9687175,"max_speed":2.9609375,"average_cadence":70,"max_cadence":83,"min_cadence":43,"average_stride_length":0,"max_stride_length":0,"min_stride_length":0,"average_ground_time":567.94446,"max_ground_time":1361,"min_ground_time":257,"average_oscillation":7.249279,"max_oscillation":13.95744,"min_oscillation":5.93663,"average_power":116.38185,"max_power":259,"average_heart_rate":0,"max_heart_rate":0,"average_leg_spring":12.822985,"calories":0,"stress":0,"max_vertical_stiffness":0.32402603357174936,"seconds_in_zones":null,"power_durations":[259,256,255.9,252.9,246.25,239.125,233.725,218.24722,212.52292,208.58333,209.73611,208.75476,211.15729,200.26575,188.32584,136.76277,0,0,0,0,0,0,0,0,0,0,0,0,0,0,0,0,0],"manufacturer":0,"serial_number":0,"product":0,"battery_voltage":0,"software_version":0,"public":false,"deleted":false,"workout_id":"","user_key":null,"timestamp_key":null,"total_power_key":null,"horizontal_power_key":null,"vertical_power_key":null,"form_power_key":null,"elevation_power_key":null,"heart_rate_key":null,"impact_key":null,"cadence_key":null,"ground_time_key":null,"oscillation_key":null,"leg_spring_key":null,"stress_key":null,"distance_key":null,"device_distance_key":null,"speed_key":null,"device_speed_key":null,"elevation_key":null,"device_elevation_key":null,"location_key":null,"file_path":"","updated_time":"2018-01-16T01:24:01.319988Z"},{"id":0,"workout_key":"","name":"Morning Run","description":"","rpe":0,"type":"","weight":86,"ftp":0,"zones":null,"start_point":{"Lat":0,"Lng":0},"end_point":{"Lat":0,"Lng":0},"location_city":"","location_state":"","location_country":"","map":{"id":"","polyline":"","summary_polyline":""},"timestamp":1515843725,"start_time":1515843725,"moving_time":2388,"elapsed_time":3150,"time_zone":"","lap_timestamp_list":null,"distance":5700,"total_elevation_gain":74.19006,"total_elevation_loss":-77.35016,"max_elevation":750.1,"min_elevation":67.29,"average_speed":2.549013,"max_speed":3.2851562,"average_cadence":81,"max_cadence":111,"min_cadence":47,"average_stride_length":0,"max_stride_length":0,"min_stride_length":0,"average_ground_time":283.94455,"max_ground_time":1233,"min_ground_time":1,"average_oscillation":7.359955,"max_oscillation":15.936376,"min_oscillation":1.130112,"average_power":168.44035,"max_power":283,"average_heart_rate":0,"max_heart_rate":0,"average_leg_spring":12.369848,"calories":0,"stress":0,"max_vertical_stiffness":0.38394810637692545,"seconds_in_zones":null,"power_durations":[283,275.75,275.1,272.675,271.96667,267.84167,261.15417,258.8611,256.33334,253.89833,251.15973,249.37738,248.26353,247.44629,246.33417,242.06389,224.825,225.11194,208.6175,176.97467,0,0,0,0,0,0,0,0,0,0,0,0,0],"manufacturer":0,"serial_number":0,"product":0,"battery_voltage":0,"software_version":0,"public":false,"deleted":false,"workout_id":"","user_key":null,"timestamp_key":null,"total_power_key":null,"horizontal_power_key":null,"vertical_power_key":null,"form_power_key":null,"elevation_power_key":null,"heart_rate_key":null,"impact_key":null,"cadence_key":null,"ground_time_key":null,"oscillation_key":null,"leg_spring_key":null,"stress_key":null,"distance_key":null,"device_distance_key":null,"speed_key":null,"device_speed_key":null,"elevation_key":null,"device_elevation_key":null,"location_key":null,"file_path":"","updated_time":"2018-01-16T01:24:04.081168Z"},{"id":0,"workout_key":"","name":"Morning Run","description":"","rpe":0,"type":"","weight":86,"ftp":0,"zones":null,"start_point":{"Lat":0,"Lng":0},"end_point":{"Lat":0,"Lng":0},"location_city":"","location_state":"","location_country":"","map":{"id":"","polyline":"","summary_polyline":""},"timestamp":1516265220,"start_time":1516265220,"moving_time":3838,"elapsed_time":4104,"time_zone":"","lap_timestamp_list":null,"distance":10380,"total_elevation_gain":108.56091,"total_elevation_loss":-87.20093,"max_elevation":757.81,"min_elevation":726.77,"average_speed":2.6903353,"max_speed":3.890625,"average_cadence":83,"max_cadence":91,"min_cadence":46,"average_stride_length":0,"max_stride_length":0,"min_stride_length":0,"average_ground_time":285.8887,"max_ground_time":1279,"min_ground_time":227,"average_oscillation":6.6775227,"max_oscillation":13.725576,"min_oscillation":5.490211,"average_power":223.11934,"max_power":338,"average_heart_rate":0,"max_heart_rate":0,"average_leg_spring":11.974772,"calories":0,"stress":0,"max_vertical_stiffness":0.4069427112804879,"seconds_in_zones":null,"power_durations":[338,331.58334,327,321.775,319.26666,313.88333,288.76666,273.65555,264.4479,263.31332,264.7139,262.82144,262.4302,262.02594,262.39334,258.685,250.81459,243.33444,241.39917,240.056,239.59445,0,0,0,0,0,0,0,0,0,0,0,0],"manufacturer":0,"serial_number":0,"product":0,"battery_voltage":0,"software_version":0,"public":false,"deleted":false,"workout_id":"","user_key":null,"timestamp_key":null,"total_power_key":null,"horizontal_power_key":null,"vertical_power_key":null,"form_power_key":null,"elevation_power_key":null,"heart_rate_key":null,"impact_key":null,"cadence_key":null,"ground_time_key":null,"oscillation_key":null,"leg_spring_key":null,"stress_key":null,"distance_key":null,"device_distance_key":null,"speed_key":null,"device_speed_key":null,"elevation_key":null,"device_elevation_key":null,"location_key":null,"file_path":"","updated_time":"2018-01-18T10:09:09.416645Z"},{"id":0,"workout_key":"","name":"Morning Run","description":"","rpe":0,"type":"","weight":86,"ftp":0,"zones":null,"start_point":{"Lat":0,"Lng":0},"end_point":{"Lat":0,"Lng":0},"location_city":"","location_state":"","location_country":"","map":{"id":"","polyline":"","summary_polyline":""},"timestamp":1516448143,"start_time":1516448143,"moving_time":4116,"elapsed_time":4686,"time_zone":"","lap_timestamp_list":null,"distance":10489,"total_elevation_gain":113.00995,"total_elevation_loss":-113.15991,"max_elevation":766.04,"min_elevation":736.01,"average_speed":2.5468922,"max_speed":3.421875,"average_cadence":82,"max_cadence":88,"min_cadence":45,"average_stride_length":0,"max_stride_length":0,"min_stride_length":0,"average_ground_time":314.05078,"max_ground_time":1356,"min_ground_time":119,"average_oscillation":6.5703607,"max_oscillation":22.84962,"min_oscillation":4.7380776,"average_power":198.0802,"max_power":298,"average_heart_rate":0,"max_heart_rate":0,"average_leg_spring":12.038084,"calories":0,"stress":0,"max_vertical_stiffness":0.4148413866178471,"seconds_in_zones":null,"power_durations":[298,291.66666,286.2,282.675,282.11667,279.61667,260.7875,260.66666,259.65,255.97667,254.48056,253.02261,251.73334,251.24538,250.80083,251.8061,248.19041,245.02916,240.0077,213.63817,212.48694,213.3294,0,0,0,0,0,0,0,0,0,0,0],"manufacturer":0,"serial_number":0,"product":0,"battery_voltage":0,"software_version":0,"public":false,"deleted":false,"workout_id":"","user_key":null,"timestamp_key":null,"total_power_key":null,"horizontal_power_key":null,"vertical_power_key":null,"form_power_key":null,"elevation_power_key":null,"heart_rate_key":null,"impact_key":null,"cadence_key":null,"ground_time_key":null,"oscillation_key":null,"leg_spring_key":null,"stress_key":null,"distance_key":null,"device_distance_key":null,"speed_key":null,"device_speed_key":null,"elevation_key":null,"device_elevation_key":null,"location_key":null,"file_path":"","updated_time":"2018-01-20T13:15:55.871944Z"},{"id":0,"workout_key":"","name":"Morning Run","description":"","rpe":0,"type":"","weight":86,"ftp":0,"zones":null,"start_point":{"Lat":0,"Lng":0},"end_point":{"Lat":0,"Lng":0},"location_city":"","location_state":"","location_country":"","map":{"id":"","polyline":"","summary_polyline":""},"timestamp":1516697591,"start_time":1516697591,"moving_time":4072,"elapsed_time":4388,"time_zone":"","lap_timestamp_list":null,"distance":10398,"total_elevation_gain":116.510254,"total_elevation_loss":-123.77026,"max_elevation":790.52,"min_elevation":758.96,"average_speed":2.5470538,"max_speed":3.6875,"average_cadence":82,"max_cadence":89,"min_cadence":44,"average_stride_length":0,"max_stride_length":0,"min_stride_length":0,"average_ground_time":299.65848,"max_ground_time":1350,"min_ground_time":70,"average_oscillation":6.771858,"max_oscillation":25.705587,"min_oscillation":5.1870236,"average_power":211.2574,"max_power":319,"average_heart_rate":0,"max_heart_rate":0,"average_leg_spring":12.315564,"calories":0,"stress":0,"max_vertical_stiffness":0.3721528552435251,"seconds_in_zones":null,"power_durations":[319,310.16666,304.1,296.575,291.13333,277.41666,273.2375,270.32224,269.21875,265.70667,261.6722,257.2988,252.98228,251.67407,249.14,242.58,235.81708,233.71945,232.31645,230.89917,230.17056,220.81429,0,0,0,0,0,0,0,0,0,0,0],"manufacturer":0,"serial_number":0,"product":0,"battery_voltage":0,"software_version":0,"public":false,"deleted":false,"workout_id":"","user_key":null,"timestamp_key":null,"total_power_key":null,"horizontal_power_key":null,"vertical_power_key":null,"form_power_key":null,"elevation_power_key":null,"heart_rate_key":null,"impact_key":null,"cadence_key":null,"ground_time_key":null,"oscillation_key":null,"leg_spring_key":null,"stress_key":null,"distance_key":null,"device_distance_key":null,"speed_key":null,"device_speed_key":null,"elevation_key":null,"device_elevation_key":null,"location_key":null,"file_path":"","updated_time":"2018-01-27T22:35:57.265611Z"},{"id":0,"workout_key":"","name":"Morning Run","description":"","rpe":0,"type":"","weight":86,"ftp":0,"zones":null,"start_point":{"Lat":0,"Lng":0},"end_point":{"Lat":0,"Lng":0},"location_city":"","location_state":"","location_country":"","map":{"id":"","polyline":"","summary_polyline":""},"timestamp":1517136398,"start_time":1517136398,"moving_time":4240,"elapsed_time":4644,"time_zone":"","lap_timestamp_list":null,"distance":10503,"total_elevation_gain":149.71045,"total_elevation_loss":-121.04047,"max_elevation":795.12,"min_elevation":760.09,"average_speed":2.3946474,"max_speed":3.0546875,"average_cadence":81,"max_cadence":117,"min_cadence":45,"average_stride_length":0,"max_stride_length":0,"min_stride_length":0,"average_ground_time":325.72177,"max_ground_time":1322,"min_ground_time":6,"average_oscillation":6.643471,"max_oscillation":20.295565,"min_oscillation":1.4429718,"average_power":194.10547,"max_power":279,"average_heart_rate":0,"max_heart_rate":0,"average_leg_spring":12.718762,"calories":0,"stress":0,"max_vertical_stiffness":0.389811569506206,"seconds_in_zones":null,"power_durations":[279,272.66666,269,263.275,256.11667,243.08333,238.54584,239.25278,235.6,233.71666,231.2125,228.89523,229.81563,222.69073,219.61917,217.97888,217.96959,211.23334,209.19687,209.027,207.91763,206.67786,0,0,0,0,0,0,0,0,0,0,0],"manufacturer":0,"serial_number":0,"product":0,"battery_voltage":0,"software_version":0,"public":false,"deleted":false,"workout_id":"","user_key":null,"timestamp_key":null,"total_power_key":null,"horizontal_power_key":null,"vertical_power_key":null,"form_power_key":null,"elevation_power_key":null,"heart_rate_key":null,"impact_key":null,"cadence_key":null,"ground_time_key":null,"oscillation_key":null,"leg_spring_key":null,"stress_key":null,"distance_key":null,"device_distance_key":null,"speed_key":null,"device_speed_key":null,"elevation_key":null,"device_elevation_key":null,"location_key":null,"file_path":"","updated_time":"2018-01-28T12:25:24.784679Z"},{"id":0,"workout_key":"","name":"Morning Run","description":"","rpe":0,"type":"","weight":86,"ftp":0,"zones":null,"start_point":{"Lat":0,"Lng":0},"end_point":{"Lat":0,"Lng":0},"location_city":"","location_state":"","location_country":"","map":{"id":"","polyline":"","summary_polyline":""},"timestamp":1517303053,"start_time":1517303053,"moving_time":4098,"elapsed_time":4438,"time_zone":"","lap_timestamp_list":null,"distance":10266,"total_elevation_gain":18.299683,"total_elevation_loss":-9.933228,"max_elevation":824.5,"min_elevation":791.13,"average_speed":2.5014296,"max_speed":3.6914062,"average_cadence":82,"max_cadence":89,"min_cadence":44,"average_stride_length":0,"max_stride_length":0,"min_stride_length":0,"average_ground_time":295.01666,"max_ground_time":1360,"min_ground_time":123,"average_oscillation":6.6993656,"max_oscillation":21.89135,"min_oscillation":3.181798,"average_power":206.68784,"max_power":319,"average_heart_rate":0,"max_heart_rate":0,"average_leg_spring":12.667457,"calories":0,"stress":0,"max_vertical_stiffness":0.38894194640512464,"seconds_in_zones":null,"power_durations":[319,317.5,315.1,305.875,299.46667,295.89166,277.14584,259.67776,254.11458,253.69667,249.96666,246.01309,243.06459,240.30278,237.82083,233.06612,230.41417,227.74083,219.18584,220.80617,220.94792,218.49155,0,0,0,0,0,0,0,0,0,0,0],"manufacturer":0,"serial_number":0,"product":0,"battery_voltage":0,"software_version":0,"public":false,"deleted":false,"workout_id":"","user_key":null,"timestamp_key":null,"total_power_key":null,"horizontal_power_key":null,"vertical_power_key":null,"form_power_key":null,"elevation_power_key":null,"heart_rate_key":null,"impact_key":null,"cadence_key":null,"ground_time_key":null,"oscillation_key":null,"leg_spring_key":null,"stress_key":null,"distance_key":null,"device_distance_key":null,"speed_key":null,"device_speed_key":null,"elevation_key":null,"device_elevation_key":null,"location_key":null,"file_path":"","updated_time":"2018-01-30T10:30:04.59838Z"},{"id":0,"workout_key":"","name":"Morning Run","description":"","rpe":0,"type":"","weight":86,"ftp":0,"zones":null,"start_point":{"Lat":0,"Lng":0},"end_point":{"Lat":0,"Lng":0},"location_city":"","location_state":"","location_country":"","map":{"id":"","polyline":"","summary_polyline":""},"timestamp":1517307149,"start_time":1517307149,"moving_time":80,"elapsed_time":342,"time_zone":"","lap_timestamp_list":null,"distance":10143,"total_elevation_gain":14.399109,"total_elevation_loss":-0.22839355,"max_elevation":824.5,"min_elevation":792.91,"average_speed":1.7177998,"max_speed":2.5664062,"average_cadence":64,"max_cadence":83,"min_cadence":44,"average_stride_length":0,"max_stride_length":0,"min_stride_length":0,"average_ground_time":748.2432,"max_ground_time":1360,"min_ground_time":277,"average_oscillation":7.3317366,"max_oscillation":21.89135,"min_oscillation":6.0989437,"average_power":31.534883,"max_power":246,"average_heart_rate":0,"max_heart_rate":0,"average_leg_spring":12.567835,"calories":0,"stress":0,"max_vertical_stiffness":0.3122740731361289,"seconds_in_zones":null,"power_durations":[246,242.75,238.4,221.475,214.81667,161.71666,89.53333,59.68889,44.766666,35.81333,0,0,0,0,0,0,0,0,0,0,0,0,0,0,0,0,0,0,0,0,0,0,0],"manufacturer":0,"serial_number":0,"product":0,"battery_voltage":0,"software_version":0,"public":false,"deleted":false,"workout_id":"","user_key":null,"timestamp_key":null,"total_power_key":null,"horizontal_power_key":null,"vertical_power_key":null,"form_power_key":null,"elevation_power_key":null,"heart_rate_key":null,"impact_key":null,"cadence_key":null,"ground_time_key":null,"oscillation_key":null,"leg_spring_key":null,"stress_key":null,"distance_key":null,"device_distance_key":null,"speed_key":null,"device_speed_key":null,"elevation_key":null,"device_elevation_key":null,"location_key":null,"file_path":"","updated_time":"2018-02-01T11:24:06.906153Z"},{"id":0,"workout_key":"","name":"Morning Run","description":"","rpe":0,"type":"","weight":86,"ftp":0,"zones":null,"start_point":{"Lat":0,"Lng":0},"end_point":{"Lat":0,"Lng":0},"location_city":"","location_state":"","location_country":"","map":{"id":"","polyline":"","summary_polyline":""},"timestamp":1517479315,"start_time":1517479315,"moving_time":3766,"elapsed_time":4072,"time_zone":"","lap_timestamp_list":null,"distance":10276,"total_elevation_gain":25.023315,"total_elevation_loss":-7.3599243,"max_elevation":811.41,"min_elevation":777.97,"average_speed":2.6457598,"max_speed":3.7265625,"average_cadence":84,"max_cadence":113,"min_cadence":47,"average_stride_length":0,"max_stride_length":0,"min_stride_length":0,"average_ground_time":272.05383,"max_ground_time":1267,"min_ground_time":2,"average_oscillation":6.8774405,"max_oscillation":17.393915,"min_oscillation":2.5234535,"average_power":214.92685,"max_power":314,"average_heart_rate":0,"max_heart_rate":0,"average_leg_spring":12.920997,"calories":0,"stress":0,"max_vertical_stiffness":0.46453936670017404,"seconds_in_zones":null,"power_durations":[314,311.66666,307.8,300.1,299.8,281.025,276.17917,270.61667,267.6375,268.88,269.2653,266.55713,263.31668,260.86203,261.185,253.77777,250.33583,244.88417,242.08896,241.61983,238.39958,0,0,0,0,0,0,0,0,0,0,0,0],"manufacturer":0,"serial_number":0,"product":0,"battery_voltage":0,"software_version":0,"public":false,"deleted":false,"workout_id":"","user_key":null,"timestamp_key":null,"total_power_key":null,"horizontal_power_key":null,"vertical_power_key":null,"form_power_key":null,"elevation_power_key":null,"heart_rate_key":null,"impact_key":null,"cadence_key":null,"ground_time_key":null,"oscillation_key":null,"leg_spring_key":null,"stress_key":null,"distance_key":null,"device_distance_key":null,"speed_key":null,"device_speed_key":null,"elevation_key":null,"device_elevation_key":null,"location_key":null,"file_path":"","updated_time":"2018-02-01T11:24:10.214785Z"},{"id":0,"workout_key":"","name":"Morning Run","description":"","rpe":0,"type":"","weight":86,"ftp":0,"zones":null,"start_point":{"Lat":0,"Lng":0},"end_point":{"Lat":0,"Lng":0},"location_city":"","location_state":"","location_country":"","map":{"id":"","polyline":"","summary_polyline":""},"timestamp":1517651985,"start_time":1517651985,"moving_time":5020,"elapsed_time":5440,"time_zone":"","lap_timestamp_list":null,"distance":13177,"total_elevation_gain":18.687988,"total_elevation_loss":-12.887085,"max_elevation":832.78,"min_elevation":801.35,"average_speed":2.6189542,"max_speed":3.796875,"average_cadence":82,"max_cadence":92,"min_cadence":43,"average_stride_length":0,"max_stride_length":0,"min_stride_length":0,"average_ground_time":329.80862,"max_ground_time":1367,"min_ground_time":129,"average_oscillation":6.665724,"max_oscillation":23.938337,"min_oscillation":3.6320183,"average_power":213.07423,"max_power":335,"average_heart_rate":0,"max_heart_rate":0,"average_leg_spring":12.349221,"calories":0,"stress":0,"max_vertical_stiffness":0.39751685728922065,"seconds_in_zones":null,"power_durations":[335,330.08334,324.65,319.65,311.73334,308.86667,303.26666,292.7,276.2354,267.465,262.00418,258.01785,257.6125,256.02686,253.77583,251.83444,252.33125,243.55917,242.40083,241.42067,239.81166,233.61238,232.37448,214.73148,0,0,0,0,0,0,0,0,0],"manufacturer":0,"serial_number":0,"product":0,"battery_voltage":0,"software_version":0,"public":false,"deleted":false,"workout_id":"","user_key":null,"timestamp_key":null,"total_power_key":null,"horizontal_power_key":null,"vertical_power_key":null,"form_power_key":null,"elevation_power_key":null,"heart_rate_key":null,"impact_key":null,"cadence_key":null,"ground_time_key":null,"oscillation_key":null,"leg_spring_key":null,"stress_key":null,"distance_key":null,"device_distance_key":null,"speed_key":null,"device_speed_key":null,"elevation_key":null,"device_elevation_key":null,"location_key":null,"file_path":"","updated_time":"2018-02-03T12:04:15.070158Z"},{"id":0,"workout_key":"","name":"Morning Run","description":"","rpe":0,"type":"","weight":86,"ftp":0,"zones":null,"start_point":{"Lat":0,"Lng":0},"end_point":{"Lat":0,"Lng":0},"location_city":"","location_state":"","location_country":"","map":{"id":"","polyline":"","summary_polyline":""},"timestamp":1517906629,"start_time":1517906629,"moving_time":3762,"elapsed_time":3998,"time_zone":"","lap_timestamp_list":null,"distance":10291,"total_elevation_gain":19.634277,"total_elevation_loss":-10.964294,"max_elevation":825.33,"min_elevation":790.32,"average_speed":2.717205,"max_speed":3.8359375,"average_cadence":83,"max_cadence":94,"min_cadence":43,"average_stride_length":0,"max_stride_length":0,"min_stride_length":0,"average_ground_time":290.48007,"max_ground_time":1367,"min_ground_time":227,"average_oscillation":6.658509,"max_oscillation":20.309324,"min_oscillation":5.252954,"average_power":226.8055,"max_power":334,"average_heart_rate":0,"max_heart_rate":0,"average_leg_spring":12.286913,"calories":0,"stress":0,"max_vertical_stiffness":0.40688690662193017,"seconds_in_zones":null,"power_durations":[334,331.58334,328.55,325.85,322.28333,312.625,306.82916,303.39166,297.58334,291.29333,281.52777,276.4619,273.48438,268.35925,264.1675,252.29167,248.25375,245.12334,243.41896,241.6385,242.93834,0,0,0,0,0,0,0,0,0,0,0,0],"manufacturer":0,"serial_number":0,"product":0,"battery_voltage":0,"software_version":0,"public":false,"deleted":false,"workout_id":"","user_key":null,"timestamp_key":null,"total_power_key":null,"horizontal_power_key":null,"vertical_power_key":null,"form_power_key":null,"elevation_power_key":null,"heart_rate_key":null,"impact_key":null,"cadence_key":null,"ground_time_key":null,"oscillation_key":null,"leg_spring_key":null,"stress_key":null,"distance_key":null,"device_distance_key":null,"speed_key":null,"device_speed_key":null,"elevation_key":null,"device_elevation_key":null,"location_key":null,"file_path":"","updated_time":"2018-02-06T10:02:48.845625Z"},{"id":0,"workout_key":"","name":"Morning Run","description":"","rpe":0,"type":"","weight":86,"ftp":0,"zones":null,"start_point":{"Lat":0,"Lng":0},"end_point":{"Lat":0,"Lng":0},"location_city":"","location_state":"","location_country":"","map":{"id":"","polyline":"","summary_polyline":""},"timestamp":1518079269,"start_time":1518079269,"moving_time":3770,"elapsed_time":4562,"time_zone":"","lap_timestamp_list":null,"distance":10229,"total_elevation_gain":25.401978,"total_elevation_loss":-10.446228,"max_elevation":802.01,"min_elevation":766.93,"average_speed":2.7063785,"max_speed":3.6796875,"average_cadence":83,"max_cadence":89,"min_cadence":43,"average_stride_length":0,"max_stride_length":0,"min_stride_length":0,"average_ground_time":279.86423,"max_ground_time":1376,"min_ground_time":233,"average_oscillation":6.8867636,"max_oscillation":16.928724,"min_oscillation":5.506232,"average_power":199.61438,"max_power":312,"average_heart_rate":0,"max_heart_rate":0,"average_leg_spring":12.65747,"calories":0,"stress":0,"max_vertical_stiffness":0.38568137472844344,"seconds_in_zones":null,"power_durations":[312,309.16666,306.85,304.325,302.81668,291.5,265.94168,256.98056,259.09167,256.35666,255.625,252.44762,251.01666,250.92036,252.1675,249.17334,248.33875,246.8189,246.21458,244.64717,243.535,216.90916,0,0,0,0,0,0,0,0,0,0,0],"manufacturer":0,"serial_number":0,"product":0,"battery_voltage":0,"software_version":0,"public":false,"deleted":false,"workout_id":"","user_key":null,"timestamp_key":null,"total_power_key":null,"horizontal_power_key":null,"vertical_power_key":null,"form_power_key":null,"elevation_power_key":null,"heart_rate_key":null,"impact_key":null,"cadence_key":null,"ground_time_key":null,"oscillation_key":null,"leg_spring_key":null,"stress_key":null,"distance_key":null,"device_distance_key":null,"speed_key":null,"device_speed_key":null,"elevation_key":null,"device_elevation_key":null,"location_key":null,"file_path":"","updated_time":"2018-02-08T10:18:51.800948Z"},{"id":0,"workout_key":"","name":"Morning Run","description":"","rpe":0,"type":"","weight":86,"ftp":0,"zones":null,"start_point":{"Lat":0,"Lng":0},"end_point":{"Lat":0,"Lng":0},"location_city":"","location_state":"","location_country":"","map":{"id":"","polyline":"","summary_polyline":""},"timestamp":1518255225,"start_time":1518255225,"moving_time":4698,"elapsed_time":5172,"time_zone":"","lap_timestamp_list":null,"distance":12598,"total_elevation_gain":6.6882935,"total_elevation_loss":-10.507996,"max_elevation":748.17,"min_elevation":741.6,"average_speed":2.6738997,"max_speed":3.2929688,"average_cadence":83,"max_cadence":89,"min_cadence":44,"average_stride_length":0,"max_stride_length":0,"min_stride_length":0,"average_ground_time":289.36374,"max_ground_time":1343,"min_ground_time":75,"average_oscillation":6.7354503,"max_oscillation":11.1388035,"min_oscillation":5.4912925,"average_power":216.38075,"max_power":307,"average_heart_rate":0,"max_heart_rate":0,"average_leg_spring":12.099759,"calories":0,"stress":0,"max_vertical_stiffness":0.37183950693624723,"seconds_in_zones":null,"power_durations":[307,303.58334,303.05,299.925,296.05,286.74167,274.2875,266.3889,258.76666,254.93167,252.5625,250.3512,248.82292,249.53334,248.70084,245.12723,244.04375,241.57861,240.23312,232.32167,233.3257,233.40036,232.66,0,0,0,0,0,0,0,0,0,0],"manufacturer":0,"serial_number":0,"product":0,"battery_voltage":0,"software_version":0,"public":false,"deleted":false,"workout_id":"","user_key":null,"timestamp_key":null,"total_power_key":null,"horizontal_power_key":null,"vertical_power_key":null,"form_power_key":null,"elevation_power_key":null,"heart_rate_key":null,"impact_key":null,"cadence_key":null,"ground_time_key":null,"oscillation_key":null,"leg_spring_key":null,"stress_key":null,"distance_key":null,"device_distance_key":null,"speed_key":null,"device_speed_key":null,"elevation_key":null,"device_elevation_key":null,"location_key":null,"file_path":"","updated_time":"2018-02-10T11:35:59.271379Z"},{"id":0,"workout_key":"","name":"Evening Run","description":"","rpe":0,"type":"","weight":86,"ftp":0,"zones":null,"start_point":{"Lat":0,"Lng":0},"end_point":{"Lat":0,"Lng":0},"location_city":"","location_state":"","location_country":"","map":{"id":"","polyline":"","summary_polyline":""},"timestamp":1518551828,"start_time":1518551828,"moving_time":5362,"elapsed_time":8354,"time_zone":"","lap_timestamp_list":null,"distance":13728,"total_elevation_gain":55.1568,"total_elevation_loss":-60.74182,"max_elevation":791.41,"min_elevation":746.29,"average_speed":2.5765452,"max_speed":5.2617188,"average_cadence":80,"max_cadence":204,"min_cadence":44,"average_stride_length":0,"max_stride_length":0,"min_stride_length":0,"average_ground_time":322.5032,"max_ground_time":1357,"min_ground_time":83,"average_oscillation":7.1181684,"max_oscillation":24.145285,"min_oscillation":1.842135,"average_power":147.04547,"max_power":469,"average_heart_rate":0,"max_heart_rate":0,"average_leg_spring":12.38498,"calories":0,"stress":0,"max_vertical_stiffness":0.414865463448696,"seconds_in_zones":null,"power_durations":[469,436.08334,405,315.525,291.58334,286.81668,277.1875,276.225,276.60626,272.05167,267.60556,269.0762,266.82083,263.7352,261.0025,251.25278,249.05792,242.37,239.88875,238.92017,238.69958,238.86084,234.1925,208.17111,187.444,183.90175,170.57944,157.45795,0,0,0,0,0],"manufacturer":0,"serial_number":0,"product":0,"battery_voltage":0,"software_version":0,"public":false,"deleted":false,"workout_id":"","user_key":null,"timestamp_key":null,"total_power_key":null,"horizontal_power_key":null,"vertical_power_key":null,"form_power_key":null,"elevation_power_key":null,"heart_rate_key":null,"impact_key":null,"cadence_key":null,"ground_time_key":null,"oscillation_key":null,"leg_spring_key":null,"stress_key":null,"distance_key":null,"device_distance_key":null,"speed_key":null,"device_speed_key":null,"elevation_key":null,"device_elevation_key":null,"location_key":null,"file_path":"","updated_time":"2018-02-13T22:17:39.811366Z"},{"id":0,"workout_key":"","name":"Noon Run","description":"","rpe":0,"type":"easy","weight":86,"ftp":0,"zones":null,"start_point":{"Lat":0,"Lng":0},"end_point":{"Lat":0,"Lng":0},"location_city":"","location_state":"","location_country":"","map":{"id":"","polyline":"","summary_polyline":""},"timestamp":1518870259,"start_time":1518870259,"moving_time":3896,"elapsed_time":4190,"time_zone":"","lap_timestamp_list":null,"distance":10341,"total_elevation_gain":23.991394,"total_elevation_loss":-5.977478,"max_elevation":758.18,"min_elevation":723.64,"average_speed":2.6467133,"max_speed":3.6015625,"average_cadence":81,"max_cadence":87,"min_cadence":45,"average_stride_length":0,"max_stride_length":0,"min_stride_length":0,"average_ground_time":289.6151,"max_ground_time":1316,"min_ground_time":237,"average_oscillation":6.8950963,"max_oscillation":10.77895,"min_oscillation":5.1278067,"average_power":220.94753,"max_power":320,"average_heart_rate":0,"max_heart_rate":0,"average_leg_spring":11.843116,"calories":0,"stress":0,"max_vertical_stiffness":0.3694612944531958,"seconds_in_zones":null,"power_durations":[320,316.41666,314.1,308.725,305.33334,290.28333,276.43332,265.625,262.32916,258.12833,259.55276,257.32144,253.04375,250.90555,251.32417,249.17056,248.04167,244.69667,241.04333,236.94083,236.8975,0,0,0,0,0,0,0,0,0,0,0,0],"manufacturer":0,"serial_number":0,"product":0,"battery_voltage":0,"software_version":0,"public":false,"deleted":false,"workout_id":"","user_key":null,"timestamp_key":null,"total_power_key":null,"horizontal_power_key":null,"vertical_power_key":null,"form_power_key":null,"elevation_power_key":null,"heart_rate_key":null,"impact_key":null,"cadence_key":null,"ground_time_key":null,"oscillation_key":null,"leg_spring_key":null,"stress_key":null,"distance_key":null,"device_distance_key":null,"speed_key":null,"device_speed_key":null,"elevation_key":null,"device_elevation_key":null,"location_key":null,"file_path":"","updated_time":"2018-02-17T14:33:22.138145Z"},{"id":0,"workout_key":"","name":"Morning Run","description":"","rpe":0,"type":"","weight":86,"ftp":0,"zones":null,"start_point":{"Lat":0,"Lng":0},"end_point":{"Lat":0,"Lng":0},"location_city":"","location_state":"","location_country":"","map":{"id":"","polyline":"","summary_polyline":""},"timestamp":1519121832,"start_time":1519121832,"moving_time":4680,"elapsed_time":4992,"time_zone":"","lap_timestamp_list":null,"distance":12543,"total_elevation_gain":24.5495,"total_elevation_loss":-10.137024,"max_elevation":795.83,"min_elevation":762.71,"average_speed":2.6699545,"max_speed":3.4101562,"average_cadence":83,"max_cadence":91,"min_cadence":45,"average_stride_length":0,"max_stride_length":0,"min_stride_length":0,"average_ground_time":289.7333,"max_ground_time":1330,"min_ground_time":77,"average_oscillation":6.632499,"max_oscillation":19.476822,"min_oscillation":3.3151453,"average_power":222.10893,"max_power":307,"average_heart_rate":0,"max_heart_rate":0,"average_leg_spring":11.924355,"calories":0,"stress":0,"max_vertical_stiffness":0.4049003938264816,"seconds_in_zones":null,"power_durations":[307,301.66666,293.45,285.475,281.71667,272.7,268.59583,258.275,257.26666,254.73,253.39166,249.94762,247.79478,246.71388,246.175,245.40834,243.34334,242.37222,239.12187,235.507,233.55861,233.55167,231.08583,0,0,0,0,0,0,0,0,0,0],"manufacturer":0,"serial_number":0,"product":0,"battery_voltage":0,"software_version":0,"public":false,"deleted":false,"workout_id":"","user_key":null,"timestamp_key":null,"total_power_key":null,"horizontal_power_key":null,"vertical_power_key":null,"form_power_key":null,"elevation_power_key":null,"heart_rate_key":null,"impact_key":null,"cadence_key":null,"ground_time_key":null,"oscillation_key":null,"leg_spring_key":null,"stress_key":null,"distance_key":null,"device_distance_key":null,"speed_key":null,"device_speed_key":null,"elevation_key":null,"device_elevation_key":null,"location_key":null,"file_path":"","updated_time":"2018-02-20T11:58:19.807081Z"},{"id":0,"workout_key":"","name":"Morning Run","description":"","rpe":0,"type":"","weight":86,"ftp":0,"zones":null,"start_point":{"Lat":0,"Lng":0},"end_point":{"Lat":0,"Lng":0},"location_city":"","location_state":"","location_country":"","map":{"id":"","polyline":"","summary_polyline":""},"timestamp":1519294379,"start_time":1519294379,"moving_time":4368,"elapsed_time":4802,"time_zone":"","lap_timestamp_list":null,"distance":12546,"total_elevation_gain":19.843811,"total_elevation_loss":-10.817139,"max_elevation":800.33,"min_elevation":767.78,"average_speed":2.864434,"max_speed":3.75,"average_cadence":84,"max_cadence":93,"min_cadence":44,"average_stride_length":0,"max_stride_length":0,"min_stride_length":0,"average_ground_time":279.99863,"max_ground_time":1338,"min_ground_time":224,"average_oscillation":6.737843,"max_oscillation":7.951563,"min_oscillation":5.659878,"average_power":230.05995,"max_power":338,"average_heart_rate":0,"max_heart_rate":0,"average_leg_spring":12.130019,"calories":0,"stress":0,"max_vertical_stiffness":0.4141578424975145,"seconds_in_zones":null,"power_durations":[338,334.33334,329.85,319.975,317.08334,306.025,292.21667,290.35556,288.68332,285.35834,286.0986,280.5869,275.76144,272.7,270.10834,262.8111,262.4,259.58472,255.56667,254.96384,254.17458,254.83595,230.25166,0,0,0,0,0,0,0,0,0,0],"manufacturer":0,"serial_number":0,"product":0,"battery_voltage":0,"software_version":0,"public":false,"deleted":false,"workout_id":"","user_key":null,"timestamp_key":null,"total_power_key":null,"horizontal_power_key":null,"vertical_power_key":null,"form_power_key":null,"elevation_power_key":null,"heart_rate_key":null,"impact_key":null,"cadence_key":null,"ground_time_key":null,"oscillation_key":null,"leg_spring_key":null,"stress_key":null,"distance_key":null,"device_distance_key":null,"speed_key":null,"device_speed_key":null,"elevation_key":null,"device_elevation_key":null,"location_key":null,"file_path":"","updated_time":"2018-02-22T11:54:22.075317Z"},{"id":0,"workout_key":"","name":"Morning Run","description":"","rpe":0,"type":"","weight":86,"ftp":0,"zones":null,"start_point":{"Lat":0,"Lng":0},"end_point":{"Lat":0,"Lng":0},"location_city":"","location_state":"","location_country":"","map":{"id":"","polyline":"","summary_polyline":""},"timestamp":1519470630,"start_time":1519470630,"moving_time":3432,"elapsed_time":3556,"time_zone":"","lap_timestamp_list":null,"distance":9694,"total_elevation_gain":5.3067017,"total_elevation_loss":-6.8914795,"max_elevation":750.39,"min_elevation":743.06,"average_speed":2.8205159,"max_speed":3.8359375,"average_cadence":83,"max_cadence":89,"min_cadence":45,"average_stride_length":0,"max_stride_length":0,"min_stride_length":0,"average_ground_time":283.39615,"max_ground_time":1358,"min_ground_time":224,"average_oscillation":6.8089037,"max_oscillation":9.419497,"min_oscillation":5.692011,"average_power":241.05058,"max_power":323,"average_heart_rate":0,"max_heart_rate":0,"average_leg_spring":11.765658,"calories":0,"stress":0,"max_vertical_stiffness":0.3913669618327128,"seconds_in_zones":null,"power_durations":[323,319.25,310.15,302.35,296.51666,287.65833,280.68332,273.61945,270.07916,268.18167,266.65833,265.7,265.9896,264.67963,264.01834,261.55832,260.89584,258.49832,255.10063,252.76567,0,0,0,0,0,0,0,0,0,0,0,0,0],"manufacturer":0,"serial_number":0,"product":0,"battery_voltage":0,"software_version":0,"public":false,"deleted":false,"workout_id":"","user_key":null,"timestamp_key":null,"total_power_key":null,"horizontal_power_key":null,"vertical_power_key":null,"form_power_key":null,"elevation_power_key":null,"heart_rate_key":null,"impact_key":null,"cadence_key":null,"ground_time_key":null,"oscillation_key":null,"leg_spring_key":null,"stress_key":null,"distance_key":null,"device_distance_key":null,"speed_key":null,"device_speed_key":null,"elevation_key":null,"device_elevation_key":null,"location_key":null,"file_path":"","updated_time":"2018-02-24T17:05:38.001166Z"},{"id":0,"workout_key":"","name":"Morning Run","description":"","rpe":0,"type":"","weight":86,"ftp":0,"zones":null,"start_point":{"Lat":0,"Lng":0},"end_point":{"Lat":0,"Lng":0},"location_city":"","location_state":"","location_country":"","map":{"id":"","polyline":"","summary_polyline":""},"timestamp":1519725957,"start_time":1519725957,"moving_time":4800,"elapsed_time":5184,"time_zone":"","lap_timestamp_list":null,"distance":12527,"total_elevation_gain":15.616333,"total_elevation_loss":-13.967041,"max_elevation":765.66,"min_elevation":735.93,"average_speed":2.6069005,"max_speed":3.7070312,"average_cadence":82,"max_cadence":88,"min_cadence":44,"average_stride_length":0,"max_stride_length":0,"min_stride_length":0,"average_ground_time":291.30807,"max_ground_time":1312,"min_ground_time":118,"average_oscillation":6.9405255,"max_oscillation":17.883863,"min_oscillation":1.130112,"average_power":215.96104,"max_power":330,"average_heart_rate":0,"max_heart_rate":0,"average_leg_spring":12.35005,"calories":0,"stress":0,"max_vertical_stiffness":0.4318827328466518,"seconds_in_zones":null,"power_durations":[330,323.91666,322.4,318.5,313.65,299.55,281.55832,270.36945,265.44168,260.29666,257.47083,256.59882,254.62291,253.23056,251.97,249.78722,248.07959,240.67361,235.53354,225.39133,225.44028,226.63286,229.13635,0,0,0,0,0,0,0,0,0,0],"manufacturer":0,"serial_number":0,"product":0,"battery_voltage":0,"software_version":0,"public":false,"deleted":false,"workout_id":"","user_key":null,"timestamp_key":null,"total_power_key":null,"horizontal_power_key":null,"vertical_power_key":null,"form_power_key":null,"elevation_power_key":null,"heart_rate_key":null,"impact_key":null,"cadence_key":null,"ground_time_key":null,"oscillation_key":null,"leg_spring_key":null,"stress_key":null,"distance_key":null,"device_distance_key":null,"speed_key":null,"device_speed_key":null,"elevation_key":null,"device_elevation_key":null,"location_key":null,"file_path":"","updated_time":"2018-02-27T11:47:41.47226Z"},{"id":0,"workout_key":"","name":"Morning Run","description":"","rpe":0,"type":"","weight":86,"ftp":170.25298384967118,"zones":[{"power_low":110.66443950228627,"power_high":136.20238707973695,"speed_low":1.249316318607883,"speed_high":1.5376200844404715,"name":"Easy"},{"power_low":136.20238707973695,"power_high":153.22768546470408,"speed_low":1.5376200844404715,"speed_high":1.7298225949955304,"name":"Moderate"},{"power_low":153.22768546470408,"power_high":170.25298384967118,"speed_low":1.7298225949955304,"speed_high":1.9220251055505893,"name":"Threshold"},{"power_low":170.25298384967118,"power_high":195.79093142712185,"speed_low":1.9220251055505893,"speed_high":2.2103288713831777,"name":"Interval"},{"power_low":195.79093142712185,"power_high":221.32887900457254,"speed_low":2.2103288713831777,"speed_high":2.498632637215766,"name":"Repetition"}],"start_point":{"Lat":0,"Lng":0},"end_point":{"Lat":0,"Lng":0},"location_city":"","location_state":"","location_country":"","map":{"id":"","polyline":"","summary_polyline":""},"timestamp":1519986579,"start_time":1519986579,"moving_time":4724,"elapsed_time":5106,"time_zone":"","lap_timestamp_list":null,"distance":12433,"total_elevation_gain":6.1329956,"total_elevation_loss":-11.805847,"max_elevation":749.83,"min_elevation":725.13,"average_speed":2.630012,"max_speed":3.375,"average_cadence":81,"max_cadence":87,"min_cadence":48,"average_stride_length":0,"max_stride_length":0,"min_stride_length":0,"average_ground_time":293.23337,"max_ground_time":1217,"min_ground_time":62,"average_oscillation":6.8692236,"max_oscillation":14.917843,"min_oscillation":0.9233126,"average_power":217.16914,"max_power":314,"average_heart_rate":0,"max_heart_rate":0,"average_leg_spring":11.94805,"calories":0,"stress":440.5443115234375,"max_vertical_stiffness":0.38182219448374666,"seconds_in_zones":[438,0,4,0,4666],"power_durations":[314,310.41666,304.9,284.175,282.08334,276.40833,264.87918,258.93332,253.74583,250.92334,249.14722,248.42024,246.89583,246.68333,246.27583,244.04445,243.11333,239.23361,235.73979,228.7545,230.0018,230.45619,230.4325,0,0,0,0,0,0,0,0,0,0],"manufacturer":0,"serial_number":0,"product":0,"battery_voltage":0,"software_version":0,"public":false,"deleted":false,"workout_id":"","user_key":null,"timestamp_key":null,"total_power_key":null,"horizontal_power_key":null,"vertical_power_key":null,"form_power_key":null,"elevation_power_key":null,"heart_rate_key":null,"impact_key":null,"cadence_key":null,"ground_time_key":null,"oscillation_key":null,"leg_spring_key":null,"stress_key":null,"distance_key":null,"device_distance_key":null,"speed_key":null,"device_speed_key":null,"elevation_key":null,"device_elevation_key":null,"location_key":null,"file_path":"","updated_time":"2018-03-02T11:59:34.067237Z"}]}
